mayarepacker/__init__.py
mayarepacker/app.py
mayarepacker/controller.py
mayarepacker/server.py
mayarepacker/view.py
mayarepacker/ui/MayaAutoPackageReloader.ui
mayarepacker-1.0.2.dist-info/LICENSE
mayarepacker-1.0.2.dist-info/METADATA
mayarepacker-1.0.2.dist-info/WHEEL
mayarepacker-1.0.2.dist-info/top_level.txt
mayarepacker-1.0.2.dist-info/RECORD
