Metadata-Version: 2.1
Name: mayarepacker
Version: 1.0.2
Summary: Automatic package reloader for Maya.
Home-page: https://github.com/InTack2/maya-auto-package-reloader
Author: Tack2
Author-email: takumi236@gmail.com
License: MIT
Project-URL: Source, https://github.com/InTack2/maya-auto-package-reloader
Project-URL: # Documentation, https://intack2.github.io/til-note/Module/boip/
Project-URL: Tracker, https://github.com/InTack2/maya-auto-package-reloader/issues
Keywords: Maya,Reloader,reload,pack,packer
Platform: UNKNOWN
Classifier: Development Status :: 5 - Production/Stable
Classifier: Intended Audience :: Developers
Classifier: License :: OSI Approved :: MIT License
Classifier: Programming Language :: Python :: 2
Classifier: Programming Language :: Python :: 2.7
Classifier: Programming Language :: Python :: 3
Classifier: Programming Language :: Python :: 3.5
Classifier: Programming Language :: Python :: 3.6
Classifier: Programming Language :: Python :: 3.7
Classifier: Programming Language :: Python :: 3.8
Classifier: Operating System :: Microsoft :: Windows :: Windows 10
Classifier: Operating System :: MacOS :: MacOS X
Classifier: Natural Language :: Japanese
Requires-Python: >=2.7
Requires-Dist: watchdog (==0.10.6)
